{"nimi":"Actual","data":[[{"seula":200.0},{"seula":150.0},{"seula":125.0},{"seula":100.0},{"seula":90.0},{"seula":80.0},{"seula":63.0},{"seula":56.0},{"seula":50.0},{"seula":45.0},{"seula":40.0},{"seula":31.5},{"seula":25.0},{"seula":22.4},{"seula":20.0},{"seula":18.0},{"seula":16.0},{"seula":12.5},{"seula":11.5},{"seula":10.0},{"seula":8.0},{"seula":6.3},{"seula":5.6},{"seula":5.0},{"seula":4.0},{"seula":2.0},{"seula":1.0},{"seula":0.5},{"seula":0.25},{"seula":0.125},{"seula":0.063}],[{"index":1,"syote":7.0},{"index":2,"syote":8.0},{"index":3,"syote":5.0},{"index":4,"syote":4.0},{"index":5,"syote":7.0},{"index":6,"syote":8.0},{"index":7,"syote":6.0},{"index":8,"syote":3.0},{"index":9,"syote":2.0},{"index":10,"syote":1.0},{"index":11,"syote":77.0},{"index":12,"syote":9.0},{"index":13,"syote":6.0},{"index":14,"syote":3.0},{"index":15,"syote":1.0},{"index":16,"syote":47.0},{"index":17,"syote":4.0},{"index":18,"syote":2.0}],[{"seularvo":200.0,"sijainti":1,"seulansijainti":0},{"seularvo":150.0,"sijainti":2,"seulansijainti":1},{"seularvo":90.0,"sijainti":3,"seulansijainti":4},{"seularvo":63.0,"sijainti":4,"seulansijainti":6},{"seularvo":56.0,"sijainti":5,"seulansijainti":7},{"seularvo":45.0,"sijainti":6,"seulansijainti":9},{"seularvo":31.5,"sijainti":7,"seulansijainti":11},{"seularvo":25.0,"sijainti":8,"seulansijainti":12},{"seularvo":20.0,"sijainti":9,"seulansijainti":14},{"seularvo":16.0,"sijainti":10,"seulansijainti":16},{"seularvo":10.0,"sijainti":11,"seulansijainti":19},{"seularvo":8.0,"sijainti":12,"seulansijainti":20},{"seularvo":5.6,"sijainti":13,"seulansijainti":22},{"seularvo":5.0,"sijainti":14,"seulansijainti":23},{"seularvo":2.0,"sijainti":15,"seulansijainti":25},{"seularvo":0.25,"sijainti":16,"seulansijainti":28},{"seularvo":0.125,"sijainti":17,"seulansijainti":29},{"seularvo":0.063,"sijainti":18,"seulansijainti":30}],false,[{"otsikko":"tyomaa","tieto":"asd"},{"otsikko":"nayteNro","tieto":"gdf"},{"otsikko":"lajite","tieto":"dsg"},{"otsikko":"date","tieto":"tbd"},{"otsikko":"osoite","tieto":"asd"},{"otsikko":"puh","tieto":"sdf"}],[{"index":17,"tulos":345.0},{"index":2,"tulos":66.0}],[{"index":15,"tulos":57.0},{"index":12,"tulos":1221.0}],[{"index":15,"tulos":66.0},{"index":12,"tulos":12.0},{"index":5,"tulos":21.0}],[{"index":7,"tulos":455.0}]]}